{"10":{"AStar":2,"Dijkstra":1},"20":{"AStar":0,"Dijkstra":6},"30":{"AStar":3,"Dijkstra":30},"40":{"AStar":8,"Dijkstra":94},"50":{"AStar":19,"Dijkstra":223},"60":{"AStar":23,"Dijkstra":440},"70":{"AStar":23,"Dijkstra":824},"80":{"AStar":49,"Dijkstra":1346},"90":{"AStar":103,"Dijkstra":2221},"100":{"AStar":105,"Dijkstra":3298},"110":{"AStar":166,"Dijkstra":4883},"120":{"AStar":425,"Dijkstra":7020},"130":{"AStar":265,"Dijkstra":9616},"140":{"AStar":278,"Dijkstra":12936},"150":{"AStar":457,"Dijkstra":17423},"160":{"AStar":765,"Dijkstra":22432},"170":{"AStar":828,"Dijkstra":28388},"180":{"AStar":1135,"Dijkstra":35780},"190":{"AStar":816,"Dijkstra":44909},"200":{"AStar":2029,"Dijkstra":55535}}